[
  {
    "name": "Alaska All Purpose Creamer",
    "qty": "1 Box (36pcs)",
    "weight": "250ml",
    "pricePiece": 50,
    "priceBox": 1500,
    "status": "In Stock",
    "expiry": "",
    "description": "Perfect for mango float and other desserts.",
    "image": "https://i.postimg.cc/Wz2d80zm/received-4391901104399999.jpg"
  },
  {
    "name": "Maximo Choco",
    "qty": "1 Box (12pcs)",
    "weight": "100grams",
    "pricePiece": 35,
    "priceBox": 350,
    "status": "In Stock",
    "expiry": "",
    "description": "ONHAND ✅

MAXIMO CHOCO

100grams x 12pcs 

FOR ONLY ₱350 ‼️‼️

YES 12 PCS NA YANG 350 mo . PERFECT PANG GIVE NGAYONG VALENTINES 💝 

ANG LAKI PA NYAN MGA MADAM AT PRAMIS SARAAP",
    "image": "https://i.postimg.cc/131Swsdz/received_765726096121883.jpg"
  },
  {
    "name": "Tang Juice+Free Pitcher",
    "qty": "1set 12pcs/1box 12inner",
    "weight": "",
    "pricePiece": 200,
    "priceBox": 2000,
    "status": "In Stock",
    "expiry": "2026-08-31",
    "description": "SALE SALE SALE ‼️‼️


✅ ₱200 per set only! ✅

TANG JUICE (12PCS) + FREE PITCHER
EXP: AUGUST 2026 

Per box : 2000/ 12inner

Magkano isang sachet nyan sa tindahan nasa 19 -22 pesos",
    "image": "https://i.postimg.cc/7PSSwVmL/received-2076145466556547.jpg"
  },
  {
    "name": "Simply Cheetos Puffs",
    "qty": "1box(12packs)",
    "weight": "226grams",
    "pricePiece": 120,
    "priceBox": 1300,
    "status": "In Stock",
    "expiry": "2026-10-31",
    "description": "*SIMPLY CHEETOS PUFFS*

12packs per box
226grams
Oct 2026

RETAIL : 120
PER BOX : 1,300

MARKET PRICE : 200 PESOS EACH ❌",
    "image": "https://i.postimg.cc/Jnjnjp2v/received-1976307987100616.jpg"
  },
  {
    "name": "Fish Red Bundle",
    "qty": "Gift Set",
    "weight": "",
    "pricePiece": 500,
    "priceBox": 0,
    "status": "In Stock",
    "expiry": "",
    "description": "*FISH RED BUNDLE*

SOSYALENG GIFT SET ✅

LAGAYAN PALANG PANALO NA 😍 + ANG DAMI PANG LAMAN 🫨

FOR ONLY 500 PESOS 💕

PERFECT PANG GIFT NGAYONG VALENTINES AT KAHIT ANONG OKASYON PA .",
    "image": "https://i.postimg.cc/rpKgyrP5/received-934038962292899.jpg"
  }
]
